babybert/__init__.py
babybert/data.py
babybert/model.py
babybert/tokenizer.py
babybert/trainer.py
babybert/utils.py
babybert/checkpoints/toy-tokenizer/tok_config.json
babybert/checkpoints/toy-tokenizer/vocab.txt
babybert-0.1.1.dist-info/METADATA
babybert-0.1.1.dist-info/WHEEL
babybert-0.1.1.dist-info/licenses/LICENSE
babybert-0.1.1.dist-info/RECORD
