Metadata-Version: 2.4
Name: babybert
Version: 0.1.1
Summary: Minimal BERT implementation in PyTorch
Project-URL: Repository, https://github.com/dross20/babybert
Author-email: Drew Ross <drewross@ku.edu>
License: MIT License
License-File: LICENSE
Keywords: bert,deep-learning,llm,machine-learning,minimal,nlp,pytorch,transformer
Classifier: Development Status :: 3 - Alpha
Classifier: License :: OSI Approved :: MIT License
Classifier: Operating System :: OS Independent
Classifier: Programming Language :: Python :: 3
Classifier: Topic :: Scientific/Engineering :: Artificial Intelligence
Requires-Python: >=3.9
Requires-Dist: numpy
Requires-Dist: torch
Requires-Dist: tqdm
Provides-Extra: dev
Requires-Dist: pytest; extra == 'dev'
Requires-Dist: ruff; extra == 'dev'
